{
    "version": "0.2.6",
    "architecture": {
        "64bit": {
            "url": "https://github.com/fengyily/shield-cli/releases/download/v0.2.6/shield-windows-amd64.zip",
            "bin": [
                "shield.exe"
            ],
            "hash": "0ee034e0620de8477f60ee652e6e38863405c3ffe91d741a030f124d1aa59c03"
        },
        "arm64": {
            "url": "https://github.com/fengyily/shield-cli/releases/download/v0.2.6/shield-windows-arm64.zip",
            "bin": [
                "shield.exe"
            ],
            "hash": "7ca6369ed8f0c8861f8a57ebd0ea8adb5a2ed9aac2631d66729c92bca98d5bf0"
        }
    },
    "homepage": "https://github.com/fengyily/shield-cli",
    "license": "Apache-2.0",
    "description": "Shield CLI - Secure Tunnel Connector"
}
